{
    "actions/lint-pr-title": "1.1.0",
    "actions/get-vault-secrets": "1.0.1",
    "actions/dockerhub-login": "1.0.0",
    "actions/send-slack-message": "1.0.0",
    "actions/push-to-gar-docker": "0.1.0",
    "actions/aws-auth": "1.0.0",
    "actions/build-push-to-dockerhub": "0.1.0",
    "actions/login-to-gar": "0.1.0",
    "actions/login-to-gcs": "0.1.0",
    "actions/argo-lint": "1.0.0",
    "actions/setup-conftest": "1.0.0",
    "actions/setup-argo": "1.0.0",
    "actions/generate-openapi-clients": "1.0.0",
    "actions/push-to-gcs": "0.1.0",
    "actions/trigger-argo-workflow": "1.0.0"
}
